{
  "@metadata": {
    "lastModified": "2025-09-30T13:52:31.987Z",
    "schemaVersion": "1"
  },
  "density": {
    "*": true,
    "unit": "g·cm[−3]",
    "value": 17
  },
  "heat": {
    "thermal_conductivity": {
      "*": true,
      "unit": "W·m[-1]·K[-1]",
      "value": 23
    }
  },
  "magnetic": {},
  "molar_volume": {
    "*": true,
    "unit": "m[3]·mol[−1]",
    "value": 0.000016
  },
  "temperature": {
    "boiling": {
      "*": true,
      "unit": "K",
      "value": 5800
    },
    "liquid": {
      "*": true,
      "unit": "K",
      "value": 3400
    },
    "melting": {
      "*": true,
      "unit": "K",
      "value": 2400
    }
  }
}
